vasvscrapper/__init__.py
vasvscrapper/attendance/__init__.py
vasvscrapper/attendance/get_attendance.py
vasvscrapper/attendance/utilities/__init__.py
vasvscrapper/attendance/utilities/attendance_scrapper.py
vasvscrapper/attendance/utilities/curate_attendance.py
vasvscrapper/attendance/utilities/merge_attendance.py
vasvscrapper/enums/__init__.py
vasvscrapper/enums/scrapper_enums.py
vasvscrapper/login/__init__.py
vasvscrapper/login/login_student.py
vasvscrapper/login/utilities/__init__.py
vasvscrapper/login/utilities/login_scrapper.py
vasvscrapper/network_requests/__init__.py
vasvscrapper/network_requests/async_requests.py
vasvscrapper/news/__init__.py
vasvscrapper/news/news_scrapper.py
vasvscrapper/news/utilities/__init__.py
vasvscrapper/news/utilities/news_scrapper.py
vasvscrapper/results/__init__.py
vasvscrapper/results/get_result.py
vasvscrapper/results/utilities/__init__.py
vasvscrapper/results/utilities/result_scrapper.py
vasvscrapper/scripts.py
vasvscrapper/status_codes/__init__.py
vasvscrapper/status_codes/attendance.py
vasvscrapper/status_codes/login.py
vasvscrapper/status_codes/news.py
vasvscrapper/status_codes/results.py
vasvscrapper-0.0.2a9.dist-info/entry_points.txt
vasvscrapper-0.0.2a9.dist-info/LICENSE
vasvscrapper-0.0.2a9.dist-info/WHEEL
vasvscrapper-0.0.2a9.dist-info/METADATA
vasvscrapper-0.0.2a9.dist-info/RECORD
